[
  {
    "timestamp": "2026-05-15T13",
    "timezone": "EST",
    "forced": false,
    "sites": [
      {
        "domain": "muvizzcom",
        "status": "success",
        "articlesCreated": 2,
        "articlesRequested": 2
      },
      {
        "domain": "wtpop",
        "status": "success",
        "articlesCreated": 2,
        "articlesRequested": 2
      },
      {
        "domain": "financenewsbase",
        "status": "success",
        "articlesCreated": 1,
        "articlesRequested": 1
      }
    ],
    "skipped": [
      {
        "domain": "chaibeseret",
        "reason": "not a preferred day (Monday, Thursday)"
      }
    ]
  },
  {
    "timestamp": "2026-05-14T13",
    "timezone": "EST",
    "forced": false,
    "sites": [
      {
        "domain": "wtpop",
        "status": "success",
        "articlesCreated": 2,
        "articlesRequested": 2
      },
      {
        "domain": "muvizzcom",
        "status": "success",
        "articlesCreated": 2,
        "articlesRequested": 2
      },
      {
        "domain": "chaibeseret",
        "status": "success",
        "articlesCreated": 1,
        "articlesRequested": 1
      },
      {
        "domain": "financenewsbase",
        "status": "success",
        "articlesCreated": 1,
        "articlesRequested": 1
      }
    ],
    "skipped": []
  },
  {
    "timestamp": "2026-05-13T13",
    "timezone": "EST",
    "forced": false,
    "sites": [
      {
        "domain": "muvizzcom",
        "status": "success",
        "articlesCreated": 1,
        "articlesRequested": 2
      },
      {
        "domain": "wtpop",
        "status": "success",
        "articlesCreated": 2,
        "articlesRequested": 2
      },
      {
        "domain": "financenewsbase",
        "status": "success",
        "articlesCreated": 1,
        "articlesRequested": 1
      }
    ],
    "skipped": [
      {
        "domain": "chaibeseret",
        "reason": "not a preferred day (Monday, Thursday)"
      }
    ]
  },
  {
    "timestamp": "2026-05-11T13",
    "timezone": "EST",
    "forced": false,
    "sites": [
      {
        "domain": "muvizzcom",
        "status": "success",
        "articlesCreated": 2,
        "articlesRequested": 2
      },
      {
        "domain": "chaibeseret",
        "status": "success",
        "articlesCreated": 1,
        "articlesRequested": 1
      },
      {
        "domain": "financenewsbase",
        "status": "success",
        "articlesCreated": 1,
        "articlesRequested": 1
      }
    ],
    "skipped": []
  },
  {
    "timestamp": "2026-05-07T13:00:04.077Z",
    "timezone": "EST",
    "forced": false,
    "sites": [
      {
        "domain": "muvizzcom",
        "status": "no_content",
        "articlesCreated": 0,
        "articlesRequested": 3,
        "message": "All 1 item(s) checked were duplicates (1 dupes)"
      }
    ],
    "skipped": []
  },
  {
    "timestamp": "2026-05-06T13:00:13.697Z",
    "timezone": "EST",
    "forced": false,
    "sites": [
      {
        "domain": "coolnews-atl",
        "status": "no_content",
        "articlesCreated": 0,
        "articlesRequested": 3,
        "message": "Aggregator returned 0 items for this site's topics"
      },
      {
        "domain": "financerooms",
        "status": "no_content",
        "articlesCreated": 0,
        "articlesRequested": 2,
        "message": "Aggregator returned 0 items for this site's topics"
      }
    ],
    "skipped": []
  },
  {
    "timestamp": "2026-05-05T13:00:15.160Z",
    "timezone": "EST",
    "forced": false,
    "sites": [
      {
        "domain": "coolnews-atl",
        "status": "no_content",
        "articlesCreated": 0,
        "articlesRequested": 3,
        "message": "Aggregator returned 0 items for this site's topics"
      },
      {
        "domain": "financerooms",
        "status": "no_content",
        "articlesCreated": 0,
        "articlesRequested": 2,
        "message": "Aggregator returned 0 items for this site's topics"
      }
    ],
    "skipped": []
  },
  {
    "timestamp": "2026-05-04T13:00:08.134Z",
    "timezone": "EST",
    "forced": false,
    "sites": [
      {
        "domain": "travel-with-atl",
        "status": "no_content",
        "articlesCreated": 0,
        "articlesRequested": 1,
        "message": "All 1 item(s) checked were duplicates (1 dupes)"
      },
      {
        "domain": "financeroom",
        "status": "no_content",
        "articlesCreated": 0,
        "articlesRequested": 3,
        "message": "Aggregator returned 0 items for this site's topics"
      }
    ],
    "skipped": [
      {
        "domain": "coolnews-atl",
        "reason": "not a preferred day (Tuesday, Wednesday, Thursday, Saturday)"
      },
      {
        "domain": "pink-life",
        "reason": "not a preferred day (Tuesday, Thursday, Friday)"
      }
    ]
  },
  {
    "timestamp": "2026-05-03T13:00:02.236Z",
    "timezone": "EST",
    "forced": false,
    "sites": [],
    "skipped": [
      {
        "domain": "coolnews-atl",
        "reason": "not a preferred day (Tuesday, Wednesday, Thursday, Saturday)"
      },
      {
        "domain": "pink-life",
        "reason": "not a preferred day (Tuesday, Thursday, Friday)"
      },
      {
        "domain": "travel-with-atl",
        "reason": "not a preferred day (Monday, Tuesday, Wednesday, Thursday, Friday)"
      }
    ]
  },
  {
    "timestamp": "2026-05-02T13:00:10.425Z",
    "timezone": "EST",
    "forced": false,
    "sites": [
      {
        "domain": "coolnews-atl",
        "status": "no_content",
        "articlesCreated": 0,
        "articlesRequested": 3,
        "message": "Aggregator returned 0 items for this site's topics"
      }
    ],
    "skipped": [
      {
        "domain": "pink-life",
        "reason": "not a preferred day (Tuesday, Thursday, Friday)"
      },
      {
        "domain": "travel-with-atl",
        "reason": "not a preferred day (Monday, Tuesday, Wednesday, Thursday, Friday)"
      }
    ]
  },
  {
    "timestamp": "2026-05-01T13:00:59.799Z",
    "timezone": "EST",
    "forced": false,
    "sites": [
      {
        "domain": "pink-life",
        "status": "success",
        "articlesCreated": 2,
        "articlesRequested": 2
      },
      {
        "domain": "travel-with-atl",
        "status": "no_content",
        "articlesCreated": 0,
        "articlesRequested": 1,
        "message": "All 1 item(s) checked were duplicates (1 dupes)"
      }
    ],
    "skipped": [
      {
        "domain": "coolnews-atl",
        "reason": "not a preferred day (Tuesday, Wednesday, Thursday, Saturday)"
      }
    ]
  },
  {
    "timestamp": "2026-04-30T13:02:04.757Z",
    "timezone": "EST",
    "forced": false,
    "sites": [
      {
        "domain": "coolnews-atl",
        "status": "no_content",
        "articlesCreated": 0,
        "articlesRequested": 3,
        "message": "Aggregator returned 0 items for this site's topics"
      },
      {
        "domain": "scienceworld",
        "status": "no_content",
        "articlesCreated": 0,
        "articlesRequested": 2,
        "message": "All 1 item(s) checked were duplicates (1 dupes)"
      },
      {
        "domain": "pink-life",
        "status": "success",
        "articlesCreated": 5,
        "articlesRequested": 5
      },
      {
        "domain": "travel-with-atl",
        "status": "no_content",
        "articlesCreated": 0,
        "articlesRequested": 1,
        "message": "All 1 item(s) checked were duplicates (1 dupes)"
      }
    ],
    "skipped": []
  },
  {
    "timestamp": "2026-04-30T08:58:55.060Z",
    "timezone": "EST",
    "forced": true,
    "sites": [
      {
        "domain": "coolnews-atl",
        "status": "no_content",
        "articlesCreated": 0,
        "articlesRequested": 3,
        "message": "Aggregator returned 0 items for this site's topics"
      },
      {
        "domain": "scienceworld",
        "status": "no_content",
        "articlesCreated": 0,
        "articlesRequested": 2,
        "message": "All 1 item(s) skipped (duplicates or filtered)"
      },
      {
        "domain": "pink-life",
        "status": "success",
        "articlesCreated": 1,
        "articlesRequested": 5
      },
      {
        "domain": "travel-with-atl",
        "status": "no_content",
        "articlesCreated": 0,
        "articlesRequested": 1,
        "message": "All 1 item(s) skipped (duplicates or filtered)"
      }
    ],
    "skipped": []
  }
]